license_header_check/__init__.py
license_header_check/__main__.py
license_header_check/version.py
license_header_check-0.2.1.data/data/data/requirements.txt
license_header_check-0.2.1.dist-info/LICENSE
license_header_check-0.2.1.dist-info/METADATA
license_header_check-0.2.1.dist-info/WHEEL
license_header_check-0.2.1.dist-info/entry_points.txt
license_header_check-0.2.1.dist-info/top_level.txt
license_header_check-0.2.1.dist-info/RECORD
