Metadata-Version: 2.1
Name: license-header-check
Version: 0.2.1
Summary: A python license header checker.
Home-page: https://github.com/TobiasSchaffner/license_header_check
Author: Tobias Schaffner
Author-email: tobiasschaffner87@outlook.com
License: MIT
Keywords: license,header
Platform: UNKNOWN
Classifier: Development Status :: 4 - Beta
Classifier: Intended Audience :: Developers
Classifier: Topic :: Software Development :: Quality Assurance
Classifier: License :: OSI Approved :: MIT License
Classifier: Programming Language :: Python :: 3.9
License-File: LICENSE
